infi.jira_cli-0.3.21-py2.7-nspkg.pth
infi/jira_cli/__init__.py
infi/jira_cli/__version__.py
infi/jira_cli/actions.py
infi/jira_cli/config.py
infi/jira_cli/confluence_adapter.py
infi/jira_cli/credential_store.py
infi/jira_cli/custom_field_editor.py
infi/jira_cli/jadmin.py
infi/jira_cli/jira_adapter.py
infi/jira_cli/jirelease.py
infi/jira_cli/jirelnotes.py
infi/jira_cli/jish.py
infi/jira_cli/jissue.py
infi/jira_cli/plugins.py
infi/jira_cli/release_notes.html
infi.jira_cli-0.3.21.dist-info/LICENSE
infi.jira_cli-0.3.21.dist-info/METADATA
infi.jira_cli-0.3.21.dist-info/WHEEL
infi.jira_cli-0.3.21.dist-info/entry_points.txt
infi.jira_cli-0.3.21.dist-info/namespace_packages.txt
infi.jira_cli-0.3.21.dist-info/top_level.txt
infi.jira_cli-0.3.21.dist-info/RECORD
