Metadata-Version: 2.1
Name: infi.jira-cli
Version: 0.3.21
Summary: JIRA command-line tools
Home-page: https://github.com/Infinidat/infi.jira_cli
Author: Arnon Yaari
Author-email: arnony@infinidat.com
License: BSD
Platform: UNKNOWN
Classifier: Intended Audience :: Developers
Classifier: Intended Audience :: System Administrators
Classifier: License :: OSI Approved :: BSD License
Classifier: Operating System :: OS Independent
Classifier: Programming Language :: Python
Classifier: Programming Language :: Python :: 2
Classifier: Programming Language :: Python :: 3
Classifier: Topic :: Software Development :: Libraries :: Python Modules
Requires-Dist: docopt
Requires-Dist: infi.credentials-store
Requires-Dist: infi.docopt-completion
Requires-Dist: infi.execute
Requires-Dist: infi.pyutils
Requires-Dist: Jinja2
Requires-Dist: jira
Requires-Dist: munch
Requires-Dist: PrettyTable
Requires-Dist: python-dateutil
Requires-Dist: requests[security]
Requires-Dist: setuptools
